EvenOddPrimeCheck/__init__.py
EvenOddPrimeCheck-0.0.2.dist-info/LICENSE.txt
EvenOddPrimeCheck-0.0.2.dist-info/METADATA
EvenOddPrimeCheck-0.0.2.dist-info/WHEEL
EvenOddPrimeCheck-0.0.2.dist-info/top_level.txt
EvenOddPrimeCheck-0.0.2.dist-info/RECORD
