Metadata-Version: 2.1
Name: EvenOddPrimeCheck
Version: 0.0.2
Summary: To test a integer if its Even / Odd / Prime
Home-page: https://github.com/riteshsharma29/
Author: Ritesh Sharma
Author-email: ritesh.sharma29@gmail.com
License: UNKNOWN
Platform: UNKNOWN
Classifier: Programming Language :: Python :: 3
Classifier: License :: OSI Approved :: MIT License
Classifier: Operating System :: OS Independent
